algebraMathGenerator
