Metadata-Version: 2.1
Name: algebraMathGenerator
Version: 0.0.6.5
Summary: An easy way to generate algebraic equations and even solve them
Home-page: UNKNOWN
Author: Megabrains
Author-email: aadibhuskute@yahoo.com
License: MIT
Keywords: algebra
Platform: UNKNOWN
Classifier: Development Status :: 5 - Production/Stable
Classifier: Intended Audience :: Education
Classifier: Operating System :: Microsoft :: Windows :: Windows 10
Classifier: License :: OSI Approved :: MIT License
Classifier: Programming Language :: Python :: 3
